estela_scrapy/__init__.py
estela_scrapy/__main__.py
estela_scrapy/env.py
estela_scrapy/extensions.py
estela_scrapy/log.py
estela_scrapy/middlewares.py
estela_scrapy/settings.py
estela_scrapy/utils.py
estela_scrapy/commands/__init__.py
estela_scrapy/commands/describe_project.py
estela_scrapy/commands/report_deploy.py
tests/__init__.py
tests/test_env.py
tests/test_main.py
tests/test_settings.py
tests/test_utils.py
estela_entrypoint-0.2.1.dist-info/METADATA
estela_entrypoint-0.2.1.dist-info/WHEEL
estela_entrypoint-0.2.1.dist-info/entry_points.txt
estela_entrypoint-0.2.1.dist-info/top_level.txt
estela_entrypoint-0.2.1.dist-info/RECORD
