Metadata-Version: 2.4
Name: estela-entrypoint
Version: 0.2.1
Summary: Scrapy entrypoint for Estela job runner
Classifier: Framework :: Scrapy
Classifier: Development Status :: 3 - Alpha
Classifier: Intended Audience :: Developers
Classifier: Operating System :: OS Independent
Classifier: Programming Language :: Python :: 3
Classifier: Topic :: Utilities
Requires-Dist: Scrapy==2.10.0
Requires-Dist: requests
Requires-Dist: redis
Requires-Dist: boto3
Requires-Dist: estela-queue-adapter
Dynamic: classifier
Dynamic: description
Dynamic: description-content-type
Dynamic: requires-dist
Dynamic: summary
